FinalProject/Random_number/LFSR.v
module LFSR(
    output reg[3:0] rand, 
    input clk, rst_n
);
reg [7:0] count;
reg [7:0] temp_count;

always @(*) begin
    rand = count[3:0] % 4'd10;
    temp_count[0] = count[0] ^ count[5] ^ count[6] ^ count[7];
    temp_count[1] = count[0];
    temp_count[2] = count[1];
    temp_count[3] = count[2];
    temp_count[4] = count[3];
    temp_count[5] = count[4];
    temp_count[6] = count[5];
    temp_count[7] = count[6];
end

always @(posedge clk, negedge rst_n) begin
    if (~rst_n) begin
        count <= 8'b00000001;
    end
    else begin
        count <= temp_count;
    end
end
endmodule

FinalProject/Random_number/LFSR_TB.v
module LFSR_TB;

parameter period = 2;

reg clk, rst_n;
wire [3:0] rand;
integer i;

LFSR U_L(
    .clk(clk),
    .rst_n(rst_n),
    .rand(rand)
);

initial begin
    clk = 0; rst_n = 0;
    for (i = 0; i < 32; i = i + 1) begin
        #(period) clk = 0; rst_n = 1;
        #(period) clk = 1; rst_n = 1;
    end
    #(period) $finish;
end

initial begin
    $dumpfile("LFSR.vcd");
    $dumpvars(0, LFSR_TB);
    $monitor($time, "rand:%D", rand);
end

endmodule

FinalProject/Random_number/LFSR.vcd
$date
	Thu May 18 15:00:18 2023
$end
$version
	Icarus Verilog
$end
$timescale
	1s
$end
$scope module LFSR_TB $end
$var wire 4 ! rand [3:0] $end
$var parameter 32 " period $end
$var reg 1 # clk $end
$var reg 1 $ rst_n $end
$var integer 32 % i [31:0] $end
$scope module U_L $end
$var wire 1 # clk $end
$var wire 1 $ rst_n $end
$var reg 8 & count [7:0] $end
$var reg 4 ' rand [3:0] $end
$var reg 8 ( temp_count [7:0] $end
$upscope $end
$upscope $end
$enddefinitions $end
$comment Show the parameter values. $end
$dumpall
b10 "
$end
#0
$dumpvars
b11 (
b1 '
b1 &
b0 %
0$
0#
b1 !
$end
#2
1$
#4
b111 (
b11 !
b11 '
b11 &
b1 %
1#
#6
0#
#8
b1111 (
b111 !
b111 '
b111 &
b10 %
1#
#10
0#
#12
b11111 (
b1111 !
b1111 '
b1111 &
b11 %
1#
#14
0#
#16
b111111 (
b11111 &
b100 %
1#
#18
0#
#20
b1111110 (
b111111 &
b101 %
1#
#22
0#
#24
b11111100 (
b1110 !
b1110 '
b1111110 &
b110 %
1#
#26
0#
#28
b11111001 (
b1100 !
b1100 '
b11111100 &
b111 %
1#
#30
0#
#32
b11110010 (
b1001 !
b1001 '
b11111001 &
b1000 %
1#
#34
0#
#36
b11100101 (
b10 !
b10 '
b11110010 &
b1001 %
1#
#38
0#
#40
b11001010 (
b101 !
b101 '
b11100101 &
b1010 %
1#
#42
0#
#44
b10010100 (
b1010 !
b1010 '
b11001010 &
b1011 %
1#
#46
0#
#48
b101001 (
b100 !
b100 '
b10010100 &
b1100 %
1#
#50
0#
#52
b1010010 (
b1001 !
b1001 '
b101001 &
b1101 %
1#
#54
0#
#56
b10100101 (
b10 !
b10 '
b1010010 &
b1110 %
1#
#58
0#
#60
b1001011 (
b101 !
b101 '
b10100101 &
b1111 %
1#
#62
0#
#64
b10010110 (
b1011 !
b1011 '
b1001011 &
b10000 %
1#
#66
0#
#68
b101101 (
b110 !
b110 '
b10010110 &
b10001 %
1#
#70
0#
#72
b1011010 (
b1101 !
b1101 '
b101101 &
b10010 %
1#
#74
0#
#76
b10110101 (
b1010 !
b1010 '
b1011010 &
b10011 %
1#
#78
0#
#80
b1101011 (
b101 !
b101 '
b10110101 &
b10100 %
1#
#82
0#
#84
b11010111 (
b1011 !
b1011 '
b1101011 &
b10101 %
1#
#86
0#
#88
b10101111 (
b111 !
b111 '
b11010111 &
b10110 %
1#
#90
0#
#92
b1011111 (
b1111 !
b1111 '
b10101111 &
b10111 %
1#
#94
0#
#96
b10111110 (
b1011111 &
b11000 %
1#
#98
0#
#100
b1111100 (
b1110 !
b1110 '
b10111110 &
b11001 %
1#
#102
0#
#104
b11111000 (
b1100 !
b1100 '
b1111100 &
b11010 %
1#
#106
0#
#108
b11110001 (
b1000 !
b1000 '
b11111000 &
b11011 %
1#
#110
0#
#112
b11100010 (
b1 !
b1 '
b11110001 &
b11100 %
1#
#114
0#
#116
b11000101 (
b10 !
b10 '
b11100010 &
b11101 %
1#
#118
0#
#120
b10001011 (
b101 !
b101 '
b11000101 &
b11110 %
1#
#122
0#
#124
b10110 (
b1011 !
b1011 '
b10001011 &
b11111 %
1#
#126
0#
#128
b101100 (
b110 !
b110 '
b10110 &
b100000 %
1#
